MANIFEST.in
README.rst
setup.cfg
setup.py
LightOn/reader.lyx
LightOn/reader.pdf
LightOn.egg-info/PKG-INFO
LightOn.egg-info/SOURCES.txt
LightOn.egg-info/dependency_links.txt
LightOn.egg-info/requires.txt
LightOn.egg-info/top_level.txt
LightOn/imag/patterns/classAdapter.png
LightOn/imag/patterns/objectAdapter.png
LightOn/imag/patterns/observer.png
LightOn/imag/patterns/underConstruction/Base Patterns.pptx
LightOn/imag/patterns/underConstruction/abstractFactory.png
LightOn/imag/patterns/underConstruction/bridge.png
LightOn/imag/patterns/underConstruction/classAdapter.png
LightOn/imag/patterns/underConstruction/composite.png
LightOn/imag/patterns/underConstruction/decorator.png
LightOn/imag/patterns/underConstruction/factoryMethod.png
LightOn/imag/patterns/underConstruction/objectAdapter.png
LightOn/imag/patterns/underConstruction/strategy.png
LightOn/imag/patterns/underConstruction/templateMethod.png
LightOn/prog/dog.py
LightOn/prog/free_functions.py
LightOn/prog/free_functions2.py
LightOn/prog/func_select.py
LightOn/prog/func_square.py
LightOn/prog/func_sum.py
LightOn/prog/lambdas.py
LightOn/prog/lambdas2.py
LightOn/prog/named_lambda.py
LightOn/prog/nature_potato.py
LightOn/prog/nature_sleeper.py
LightOn/prog/neighbours_dog.py
LightOn/prog/nonfunc_select.py
LightOn/prog/nonfunc_square.py
LightOn/prog/nonfunc_sum.py
LightOn/prog/radio_vision.py
LightOn/prog/sort.py
LightOn/prog/sort2.py
LightOn/prog/walking_the_dogs.py
LightOn/prog/datastructures/lists.py
LightOn/prog/datastructures/tuples.py
LightOn/prog/dog_walker/bosses.py
LightOn/prog/dog_walker/dog_walker.py
LightOn/prog/dog_walker/dogs.py
LightOn/prog/dog_walker/func_walker.py
LightOn/prog/dog_walker/poly_walker.py
LightOn/prog/intro_pyglet/arrow.png
LightOn/prog/intro_pyglet/cloud.png
LightOn/prog/intro_pyglet/drifting_sprites.py
LightOn/prog/intro_pyglet/egg.png
LightOn/prog/intro_pyglet/heart.png
LightOn/prog/intro_pyglet/lightning.png
LightOn/prog/intro_pyglet/lists.py
LightOn/prog/intro_pyglet/star.png
LightOn/prog/patterns/callChaining.py
LightOn/prog/patterns/callChainingLiterate.py
LightOn/prog/patterns/classAdapter.py
