Metadata-Version: 1.1
Name: LightOn
Version: 0.0.18
Summary: LightOn - A lightweight Python course taking beginners seriously
Home-page: https://github.com/JdeH/LightOn/
Author: Jacques de Hooge
Author-email: jacques.de.hooge@qquick.org
License: qQuickLicence
Keywords: python,tutorial,course,primer,object,functional,pong
Platform: UNKNOWN
Classifier: Development Status :: 2 - Pre-Alpha
Classifier: Intended Audience :: Education
Classifier: Natural Language :: English
Classifier: License :: Other/Proprietary License
Classifier: Topic :: Software Development :: Libraries :: Python Modules
Classifier: Operating System :: OS Independent
Classifier: Programming Language :: Python :: 3
